[{"verse":"02-16","book":"Genesis","quote":"Jehovah God also gave this command to the man: “From every tree of the garden you may eat to satisfaction."},{"verse":"02-16","book":"Exodus","quote":"Now the priest of Midʹi·an had seven daughters, and these came to draw water and to fill the troughs to water their father’s flock."},{"verse":"02-16","book":"Ezra","quote":"the sons of Aʹter, of Hez·e·kiʹah, 98;"},{"verse":"02-16","book":"Luke","quote":"And they went quickly and found Mary as well as Joseph, and the infant lying in the manger."}]